rstt/__init__.py
rstt/config.py
rstt/game/__init__.py
rstt/game/match.py
rstt/player/__init__.py
rstt/player/basicplayer.py
rstt/player/gaussian.py
rstt/player/player.py
rstt/player/playerTVS.py
rstt/ranking/__init__.py
rstt/ranking/datamodel.py
rstt/ranking/inferer/__init__.py
rstt/ranking/inferer/elo.py
rstt/ranking/inferer/eventscoring.py
rstt/ranking/inferer/glicko.py
rstt/ranking/inferer/glicko2.py
rstt/ranking/inferer/playerlevel.py
rstt/ranking/inferer/playerwinprc.py
rstt/ranking/observer/__init__.py
rstt/ranking/observer/gameObserver.py
rstt/ranking/observer/obs.py
rstt/ranking/observer/playerObserver.py
rstt/ranking/ranking.py
rstt/ranking/rating.py
rstt/ranking/standard/__init__.py
rstt/ranking/standard/basicElo.py
rstt/ranking/standard/basicGlicko.py
rstt/ranking/standard/basicOS.py
rstt/ranking/standard/consensus.py
rstt/ranking/standard/successRanking.py
rstt/ranking/standing.py
rstt/scheduler/__init__.py
rstt/scheduler/matchmaking/__init__.py
rstt/scheduler/scheduler.py
rstt/scheduler/tournament/__init__.py
rstt/scheduler/tournament/competition.py
rstt/scheduler/tournament/groups.py
rstt/scheduler/tournament/knockout.py
rstt/scheduler/tournament/random.py
rstt/scheduler/tournament/snake.py
rstt/scheduler/tournament/swissbracket.py
rstt/solver/__init__.py
rstt/solver/solvers.py
rstt/stypes.py
rstt/utils/__init__.py
rstt/utils/competition.py
rstt/utils/constants.py
rstt/utils/functions.py
rstt/utils/matching.py
rstt/utils/observer.py
rstt/utils/utils.py
rstt-0.6.7.1.dist-info/LICENSE
rstt-0.6.7.1.dist-info/METADATA
rstt-0.6.7.1.dist-info/WHEEL
rstt-0.6.7.1.dist-info/RECORD
