Metadata-Version: 2.3
Name: rstt
Version: 0.6.7.1
Summary: Ranking Simulation Testing Tool
License: MIT
Author: Bucher David
Author-email: davidbucherdev@gmail.com
Requires-Python: >=3.10
Classifier: Development Status :: 3 - Alpha
Classifier: Intended Audience :: Science/Research
Classifier: Topic :: Scientific/Engineering
Classifier: Topic :: Games/Entertainment
Classifier: Topic :: Games/Entertainment :: Simulation
Classifier: Typing :: Typed
Requires-Dist: names (>=0.3.0,<0.4.0)
Requires-Dist: numpy (>=2.2.2,<3.0.0)
Requires-Dist: typeguard (>=3.0.0,<3.0.2)
Project-URL: Documentation, https://rstt.readthedocs.io/en/latest/
Project-URL: Repository, https://github.com/Ematrion/rstt
